random_symplectic-0.0.2.dist-info/licenses/LICENSE
randomsymplectic/__init__.py
randomsymplectic/dnary_arithmetic.py
randomsymplectic/dnary_array.py
randomsymplectic/validation.py
randomsymplectic/version.py
random_symplectic-0.0.2.dist-info/METADATA
random_symplectic-0.0.2.dist-info/WHEEL
random_symplectic-0.0.2.dist-info/top_level.txt
random_symplectic-0.0.2.dist-info/RECORD
