Metadata-Version: 2.4
Name: random-symplectic
Version: 0.0.2
Summary: Random d-nary symplectic matrices for qudit Clifford gates.
Author-email: "Zachary C. Coleman" <coleman.zacharyc@gmail.com>
License-Expression: MIT
Project-URL: Homepage, https://github.com/zccoleman/random-symplectic
Project-URL: docs, https://zccoleman.github.io/random-symplectic/
Keywords: quantum computing,qudit,symplectic,clifford
Classifier: Programming Language :: Python :: 3
Requires-Python: >=3.8
License-File: LICENSE
Requires-Dist: numpy
Requires-Dist: sympy
Dynamic: license-file
